pyscipopt_ml/__init__.py
pyscipopt_ml/_version.py
pyscipopt_ml/add_predictor.py
pyscipopt_ml/exceptions.py
pyscipopt_ml/registered_predictors.py
pyscipopt_ml/keras/__init__.py
pyscipopt_ml/keras/keras.py
pyscipopt_ml/lightgbm/__init__.py
pyscipopt_ml/lightgbm/lgbgetter.py
pyscipopt_ml/lightgbm/lightgbm_constr.py
pyscipopt_ml/modelling/__init__.py
pyscipopt_ml/modelling/base_predictor_constraint.py
pyscipopt_ml/modelling/get_convertor.py
pyscipopt_ml/modelling/classification/__init__.py
pyscipopt_ml/modelling/classification/argmax_model.py
pyscipopt_ml/modelling/classification/max_model.py
pyscipopt_ml/modelling/decision_tree/__init__.py
pyscipopt_ml/modelling/decision_tree/decision_tree_model.py
pyscipopt_ml/modelling/gradient_boosting/__init__.py
pyscipopt_ml/modelling/gradient_boosting/aggregate_tree_model.py
pyscipopt_ml/modelling/neuralnet/__init__.py
pyscipopt_ml/modelling/neuralnet/activations.py
pyscipopt_ml/modelling/neuralnet/layers.py
pyscipopt_ml/modelling/neuralnet/neural_net.py
pyscipopt_ml/onnx/__init__.py
pyscipopt_ml/onnx/neural_net_onnx.py
pyscipopt_ml/sklearn/__init__.py
pyscipopt_ml/sklearn/base_regression.py
pyscipopt_ml/sklearn/centroid_cluster.py
pyscipopt_ml/sklearn/decision_tree.py
pyscipopt_ml/sklearn/gradient_boosting.py
pyscipopt_ml/sklearn/linear_regression.py
pyscipopt_ml/sklearn/logistic_regression.py
pyscipopt_ml/sklearn/mlp.py
pyscipopt_ml/sklearn/multi_output.py
pyscipopt_ml/sklearn/pipeline.py
pyscipopt_ml/sklearn/pls.py
pyscipopt_ml/sklearn/preprocessing.py
pyscipopt_ml/sklearn/random_forest.py
pyscipopt_ml/sklearn/skgetter.py
pyscipopt_ml/sklearn/support_vector.py
pyscipopt_ml/torch/__init__.py
pyscipopt_ml/torch/sequential.py
pyscipopt_ml/xgboost/__init__.py
pyscipopt_ml/xgboost/xgbgetter.py
pyscipopt_ml/xgboost/xgboost_constr.py
pyscipopt_ml-1.4.1.dist-info/LICENSE
pyscipopt_ml-1.4.1.dist-info/METADATA
pyscipopt_ml-1.4.1.dist-info/WHEEL
pyscipopt_ml-1.4.1.dist-info/top_level.txt
pyscipopt_ml-1.4.1.dist-info/RECORD
