Metadata-Version: 2.2
Name: PySCIPOpt-ML
Version: 1.4.1
Summary: automatically formulate and embed ML models into MIPs with SCIP
Author: Mark Turner - Zuse Institute Berlin
License: Apache-2.0
Project-URL: Repository, https://github.com/Opt-Mucca/PySCIPOpt-ML
Project-URL: Documentation, https://pyscipopt-ml.readthedocs.io/en/stable/
Project-URL: Bug Tracker, https://github.com/Opt-Mucca/PySCIPOpt-ML/issues
Keywords: mixed-integer programming,SCIP,scikit-learn,pytorch,xgboost,lightgbm,keras,ml
Requires-Python: >=3.8
License-File: LICENSE
Requires-Dist: numpy
Requires-Dist: pyscipopt>=5.4.1
